yapapi/__init__.py
yapapi/agreements_pool.py
yapapi/config.py
yapapi/contrib/__init__.py
yapapi/contrib/service/__init__.py
yapapi/contrib/service/chunk.py
yapapi/contrib/service/http_proxy.py
yapapi/contrib/service/socket_proxy.py
yapapi/contrib/strategy/__init__.py
yapapi/contrib/strategy/provider_filter.py
yapapi/ctx.py
yapapi/engine.py
yapapi/event_dispatcher.py
yapapi/events.py
yapapi/executor/__init__.py
yapapi/executor/_smartq.py
yapapi/executor/task.py
yapapi/golem.py
yapapi/invoice_manager.py
yapapi/log.py
yapapi/network.py
yapapi/payload/__init__.py
yapapi/payload/manifest.py
yapapi/payload/package.py
yapapi/payload/vm.py
yapapi/props/__init__.py
yapapi/props/base.py
yapapi/props/builder.py
yapapi/props/com.py
yapapi/props/inf.py
yapapi/py.typed
yapapi/rest/__init__.py
yapapi/rest/activity.py
yapapi/rest/common.py
yapapi/rest/configuration.py
yapapi/rest/market.py
yapapi/rest/net.py
yapapi/rest/payment.py
yapapi/rest/resource.py
yapapi/script/__init__.py
yapapi/script/capture.py
yapapi/script/command.py
yapapi/services/__init__.py
yapapi/services/cluster.py
yapapi/services/service.py
yapapi/services/service_runner.py
yapapi/services/service_state.py
yapapi/storage/__init__.py
yapapi/storage/gftp.py
yapapi/storage/webdav.py
yapapi/strategy/__init__.py
yapapi/strategy/base.py
yapapi/strategy/decrease_score_unconfirmed.py
yapapi/strategy/dummy.py
yapapi/strategy/least_expensive.py
yapapi/strategy/wrapping_strategy.py
yapapi/utils.py
yapapi-0.13.1.dist-info/LICENSE
yapapi-0.13.1.dist-info/METADATA
yapapi-0.13.1.dist-info/WHEEL
yapapi-0.13.1.dist-info/RECORD
