Metadata-Version: 2.1
Name: yapapi
Version: 0.13.1
Summary: High-level Python API for the New Golem
Home-page: https://github.com/golemfactory/yapapi
License: LGPL-3.0-or-later
Author: GolemFactory
Author-email: contact@golem.network
Requires-Python: >=3.8,<4.0
Classifier: Development Status :: 3 - Alpha
Classifier: Framework :: AsyncIO
Classifier: License :: OSI Approved :: GNU Lesser General Public License v3 or later (LGPLv3+)
Classifier: Programming Language :: Python :: 3
Classifier: Programming Language :: Python :: 3.8
Classifier: Programming Language :: Python :: 3.9
Classifier: Programming Language :: Python :: 3.10
Classifier: Programming Language :: Python :: 3.11
Classifier: Programming Language :: Python :: 3.12
Classifier: Programming Language :: Python :: 3.13
Classifier: Topic :: Software Development :: Libraries :: Python Modules
Classifier: Topic :: System :: Distributed Computing
Provides-Extra: docs
Requires-Dist: Deprecated (>=1.2.12,<2.0.0)
Requires-Dist: aiohttp (>=3.8,<4.0)
Requires-Dist: aiohttp-sse-client (>=0.2.1,<0.3.0)
Requires-Dist: alive_progress (==3.1)
Requires-Dist: async_exit_stack (>=1.0.1,<2.0.0)
Requires-Dist: attrs (>=19.3)
Requires-Dist: colorama (>=0.4.4,<0.5.0)
Requires-Dist: jsonrpc-base (>=1.0.3,<2.0.0)
Requires-Dist: pip
Requires-Dist: python-statemachine (>=0.8.0,<0.9.0)
Requires-Dist: semantic-version (>=2.8,<3.0)
Requires-Dist: setuptools
Requires-Dist: sphinx (>=4.0.1,<5.0.0) ; extra == "docs"
Requires-Dist: sphinx-autodoc-typehints (>=1.12.0,<2.0.0) ; extra == "docs"
Requires-Dist: sphinx-rtd-theme (>=1.0.0,<2.0.0) ; extra == "docs"
Requires-Dist: toml (>=0.10.1,<0.11.0)
Requires-Dist: ya-aioclient (>=0.6.4,<0.7.0)
Project-URL: Documentation, https://yapapi.readthedocs.io/en/stable/api.html
Project-URL: Repository, https://github.com/golemfactory/yapapi
